<?xml version="1.0" encoding="UTF-8"?>
<!DOCTYPE mapper PUBLIC "-//mybatis.org//DTD Mapper 3.0//EN" "http://mybatis.org/dtd/mybatis-3-mapper.dtd">
<mapper namespace="ru.gb.mybatis.dao.OrderStatusMapper">
  <resultMap id="BaseResultMap" type="ru.gb.mybatis.model.OrderStatus">
    <!--
      WARNING - @mbg.generated
      This element is automatically generated by MyBatis Generator, do not modify.
      This element was generated on Tue Apr 19 21:43:39 MSK 2022.
    -->
    <id column="order_status_id" jdbcType="VARCHAR" property="orderStatusId" />
    <result column="update_at" jdbcType="TIMESTAMP" property="updateAt" />
    <result column="sale_id" jdbcType="VARCHAR" property="saleId" />
    <result column="status_name_id" jdbcType="INTEGER" property="statusNameId" />
  </resultMap>
  <sql id="Example_Where_Clause">
    <!--
      WARNING - @mbg.generated
      This element is automatically generated by MyBatis Generator, do not modify.
      This element was generated on Tue Apr 19 21:43:39 MSK 2022.
    -->
    <where>
      <foreach collection="oredCriteria" item="criteria" separator="or">
        <if test="criteria.valid">
          <trim prefix="(" prefixOverrides="and" suffix=")">
            <foreach collection="criteria.criteria" item="criterion">
              <choose>
                <when test="criterion.noValue">
                  and ${criterion.condition}
                </when>
                <when test="criterion.singleValue">
                  and ${criterion.condition} #{criterion.value}
                </when>
                <when test="criterion.betweenValue">
                  and ${criterion.condition} #{criterion.value} and #{criterion.secondValue}
                </when>
                <when test="criterion.listValue">
                  and ${criterion.condition}
                  <foreach close=")" collection="criterion.value" item="listItem" open="(" separator=",">
                    #{listItem}
                  </foreach>
                </when>
              </choose>
            </foreach>
          </trim>
        </if>
      </foreach>
    </where>
  </sql>
  <sql id="Update_By_Example_Where_Clause">
    <!--
      WARNING - @mbg.generated
      This element is automatically generated by MyBatis Generator, do not modify.
      This element was generated on Tue Apr 19 21:43:39 MSK 2022.
    -->
    <where>
      <foreach collection="example.oredCriteria" item="criteria" separator="or">
        <if test="criteria.valid">
          <trim prefix="(" prefixOverrides="and" suffix=")">
            <foreach collection="criteria.criteria" item="criterion">
              <choose>
                <when test="criterion.noValue">
                  and ${criterion.condition}
                </when>
                <when test="criterion.singleValue">
                  and ${criterion.condition} #{criterion.value}
                </when>
                <when test="criterion.betweenValue">
                  and ${criterion.condition} #{criterion.value} and #{criterion.secondValue}
                </when>
                <when test="criterion.listValue">
                  and ${criterion.condition}
                  <foreach close=")" collection="criterion.value" item="listItem" open="(" separator=",">
                    #{listItem}
                  </foreach>
                </when>
              </choose>
            </foreach>
          </trim>
        </if>
      </foreach>
    </where>
  </sql>
  <sql id="Base_Column_List">
    <!--
      WARNING - @mbg.generated
      This element is automatically generated by MyBatis Generator, do not modify.
      This element was generated on Tue Apr 19 21:43:39 MSK 2022.
    -->
    order_status_id, update_at, sale_id, status_name_id
  </sql>
  <select id="selectByExample" parameterType="ru.gb.mybatis.model.OrderStatusExample" resultMap="BaseResultMap">
    <!--
      WARNING - @mbg.generated
      This element is automatically generated by MyBatis Generator, do not modify.
      This element was generated on Tue Apr 19 21:43:39 MSK 2022.
    -->
    select
    <if test="distinct">
      distinct
    </if>
    <include refid="Base_Column_List" />
    from order_status
    <if test="_parameter != null">
      <include refid="Example_Where_Clause" />
    </if>
    <if test="orderByClause != null">
      order by ${orderByClause}
    </if>
  </select>
  <select id="selectByPrimaryKey" parameterType="java.lang.String" resultMap="BaseResultMap">
    <!--
      WARNING - @mbg.generated
      This element is automatically generated by MyBatis Generator, do not modify.
      This element was generated on Tue Apr 19 21:43:39 MSK 2022.
    -->
    select 
    <include refid="Base_Column_List" />
    from order_status
    where order_status_id = #{orderStatusId,jdbcType=VARCHAR}
  </select>
  <delete id="deleteByPrimaryKey" parameterType="java.lang.String">
    <!--
      WARNING - @mbg.generated
      This element is automatically generated by MyBatis Generator, do not modify.
      This element was generated on Tue Apr 19 21:43:39 MSK 2022.
    -->
    delete from order_status
    where order_status_id = #{orderStatusId,jdbcType=VARCHAR}
  </delete>
  <delete id="deleteByExample" parameterType="ru.gb.mybatis.model.OrderStatusExample">
    <!--
      WARNING - @mbg.generated
      This element is automatically generated by MyBatis Generator, do not modify.
      This element was generated on Tue Apr 19 21:43:39 MSK 2022.
    -->
    delete from order_status
    <if test="_parameter != null">
      <include refid="Example_Where_Clause" />
    </if>
  </delete>
  <insert id="insert" parameterType="ru.gb.mybatis.model.OrderStatus">
    <!--
      WARNING - @mbg.generated
      This element is automatically generated by MyBatis Generator, do not modify.
      This element was generated on Tue Apr 19 21:43:39 MSK 2022.
    -->
    insert into order_status (order_status_id, update_at, sale_id, 
      status_name_id)
    values (#{orderStatusId,jdbcType=VARCHAR}, #{updateAt,jdbcType=TIMESTAMP}, #{saleId,jdbcType=VARCHAR}, 
      #{statusNameId,jdbcType=INTEGER})
  </insert>
  <insert id="insertSelective" parameterType="ru.gb.mybatis.model.OrderStatus">
    <!--
      WARNING - @mbg.generated
      This element is automatically generated by MyBatis Generator, do not modify.
      This element was generated on Tue Apr 19 21:43:39 MSK 2022.
    -->
    insert into order_status
    <trim prefix="(" suffix=")" suffixOverrides=",">
      <if test="orderStatusId != null">
        order_status_id,
      </if>
      <if test="updateAt != null">
        update_at,
      </if>
      <if test="saleId != null">
        sale_id,
      </if>
      <if test="statusNameId != null">
        status_name_id,
      </if>
    </trim>
    <trim prefix="values (" suffix=")" suffixOverrides=",">
      <if test="orderStatusId != null">
        #{orderStatusId,jdbcType=VARCHAR},
      </if>
      <if test="updateAt != null">
        #{updateAt,jdbcType=TIMESTAMP},
      </if>
      <if test="saleId != null">
        #{saleId,jdbcType=VARCHAR},
      </if>
      <if test="statusNameId != null">
        #{statusNameId,jdbcType=INTEGER},
      </if>
    </trim>
  </insert>
  <select id="countByExample" parameterType="ru.gb.mybatis.model.OrderStatusExample" resultType="java.lang.Long">
    <!--
      WARNING - @mbg.generated
      This element is automatically generated by MyBatis Generator, do not modify.
      This element was generated on Tue Apr 19 21:43:39 MSK 2022.
    -->
    select count(*) from order_status
    <if test="_parameter != null">
      <include refid="Example_Where_Clause" />
    </if>
  </select>
  <update id="updateByExampleSelective" parameterType="map">
    <!--
      WARNING - @mbg.generated
      This element is automatically generated by MyBatis Generator, do not modify.
      This element was generated on Tue Apr 19 21:43:39 MSK 2022.
    -->
    update order_status
    <set>
      <if test="record.orderStatusId != null">
        order_status_id = #{record.orderStatusId,jdbcType=VARCHAR},
      </if>
      <if test="record.updateAt != null">
        update_at = #{record.updateAt,jdbcType=TIMESTAMP},
      </if>
      <if test="record.saleId != null">
        sale_id = #{record.saleId,jdbcType=VARCHAR},
      </if>
      <if test="record.statusNameId != null">
        status_name_id = #{record.statusNameId,jdbcType=INTEGER},
      </if>
    </set>
    <if test="_parameter != null">
      <include refid="Update_By_Example_Where_Clause" />
    </if>
  </update>
  <update id="updateByExample" parameterType="map">
    <!--
      WARNING - @mbg.generated
      This element is automatically generated by MyBatis Generator, do not modify.
      This element was generated on Tue Apr 19 21:43:39 MSK 2022.
    -->
    update order_status
    set order_status_id = #{record.orderStatusId,jdbcType=VARCHAR},
      update_at = #{record.updateAt,jdbcType=TIMESTAMP},
      sale_id = #{record.saleId,jdbcType=VARCHAR},
      status_name_id = #{record.statusNameId,jdbcType=INTEGER}
    <if test="_parameter != null">
      <include refid="Update_By_Example_Where_Clause" />
    </if>
  </update>
  <update id="updateByPrimaryKeySelective" parameterType="ru.gb.mybatis.model.OrderStatus">
    <!--
      WARNING - @mbg.generated
      This element is automatically generated by MyBatis Generator, do not modify.
      This element was generated on Tue Apr 19 21:43:39 MSK 2022.
    -->
    update order_status
    <set>
      <if test="updateAt != null">
        update_at = #{updateAt,jdbcType=TIMESTAMP},
      </if>
      <if test="saleId != null">
        sale_id = #{saleId,jdbcType=VARCHAR},
      </if>
      <if test="statusNameId != null">
        status_name_id = #{statusNameId,jdbcType=INTEGER},
      </if>
    </set>
    where order_status_id = #{orderStatusId,jdbcType=VARCHAR}
  </update>
  <update id="updateByPrimaryKey" parameterType="ru.gb.mybatis.model.OrderStatus">
    <!--
      WARNING - @mbg.generated
      This element is automatically generated by MyBatis Generator, do not modify.
      This element was generated on Tue Apr 19 21:43:39 MSK 2022.
    -->
    update order_status
    set update_at = #{updateAt,jdbcType=TIMESTAMP},
      sale_id = #{saleId,jdbcType=VARCHAR},
      status_name_id = #{statusNameId,jdbcType=INTEGER}
    where order_status_id = #{orderStatusId,jdbcType=VARCHAR}
  </update>
</mapper>